recruiter/utils/__init__.py
recruiter/utils/lazy.py
recruiter/utils/lazy_test.py
recruiter/utils/service_config.py
recruiter/utils/service_config_test.py
recruiter_utils-0.0.3.dist-info/WHEEL
recruiter_utils-0.0.3.dist-info/METADATA
recruiter_utils-0.0.3.dist-info/RECORD
